moonstuff/__init__.py
moonstuff/admin.py
moonstuff/apps.py
moonstuff/auth_hooks.py
moonstuff/models.py
moonstuff/parser.py
moonstuff/providers.py
moonstuff/tasks.py
moonstuff/urls.py
moonstuff/views.py
moonstuff/management/commands/__init__.py
moonstuff/management/commands/moonstuff_preload_data.py
moonstuff/migrations/0001_initial.py
moonstuff/migrations/0002_remove_material_model.py
moonstuff/migrations/0003_OtO_TrackingCharacter_Character.py
moonstuff/migrations/0004_delete_trackingcharacter.py
moonstuff/migrations/0005_trackingcharacter.py
moonstuff/migrations/0006_auto_20210617_0247.py
moonstuff/migrations/__init__.py
moonstuff/static/moonstuff/css/style.css
moonstuff/templates/moonstuff/add_scan.html
moonstuff/templates/moonstuff/base.html
moonstuff/templates/moonstuff/dashboard.html
moonstuff/templates/moonstuff/menu.html
moonstuff/templates/moonstuff/moon_info.html
moonstuff/templates/moonstuff/moon_info_ajax.html
moonstuff/templatetags/__init__.py
moonstuff/templatetags/filters.py
moonstuff/tests/__init__.py
moonstuff/tests/parser_strings.py
moonstuff/tests/test_filters.py
moonstuff/tests/test_models.py
moonstuff/tests/test_parser.py
moonstuff/tests/test_tasks.py
tests/__init__.py
tests/celery.py
tests/test_settings.py
tests/urls.py
tests/views.py
aa_moonstuff-2.0.4.dist-info/LICENSE
aa_moonstuff-2.0.4.dist-info/METADATA
aa_moonstuff-2.0.4.dist-info/WHEEL
aa_moonstuff-2.0.4.dist-info/top_level.txt
aa_moonstuff-2.0.4.dist-info/RECORD
