Metadata-Version: 2.1
Name: aa-moonstuff
Version: 2.0.4
Summary: A plugin for publishing moon extractions, and keeping track of moon scan data.
Home-page: https://gitlab.com/colcrunch/aa-moonstuff
Author: Col Crunch
Author-email: it-team@serin.space
License: GPLv3
Platform: UNKNOWN
Classifier: Environment :: Web Environment
Classifier: Framework :: Django
Classifier: Framework :: Django :: 3.1
Classifier: Intended Audience :: Developers
Classifier: Operating System :: POSIX :: Linux
Classifier: Programming Language :: Python
Classifier: Programming Language :: Python :: 3
Classifier: Programming Language :: Python :: 3.6
Classifier: Programming Language :: Python :: 3.7
Classifier: Programming Language :: Python :: 3.8
Classifier: License :: OSI Approved :: GNU General Public License v3 (GPLv3)
Classifier: Topic :: Internet :: WWW/HTTP
Classifier: Topic :: Internet :: WWW/HTTP :: Dynamic Content
Requires-Python: ~=3.6
License-File: LICENSE
Requires-Dist: requests
Requires-Dist: allianceauth (>=2.8.1)
Requires-Dist: django-esi (>=2.0.4)
Requires-Dist: django-eveuniverse (>=0.8.0)
Requires-Dist: typing ; python_version=="3.6"
Provides-Extra: testing
